[
    {
      "name": "order_id",
      "mode": "NULLABLE",
      "type": "STRING",
      "description": "",
      "fields": []
    },
    {
      "name": "order_item_id",
      "mode": "NULLABLE",
      "type": "INTEGER",
      "description": "",
      "fields": []
    },
    {
      "name": "product_id",
      "mode": "NULLABLE",
      "type": "STRING",
      "description": "",
      "fields": []
    },
    {
      "name": "seller_id",
      "mode": "NULLABLE",
      "type": "STRING",
      "description": "",
      "fields": []
    },
    {
      "name": "shipping_limit_date",
      "mode": "NULLABLE",
      "type": "TIMESTAMP",
      "description": "",
      "fields": []
    },
    {
      "name": "price",
      "mode": "NULLABLE",
      "type": "FLOAT",
      "description": "",
      "fields": []
    },
    {
      "name": "freight_value",
      "mode": "NULLABLE",
      "type": "FLOAT",
      "description": "",
      "fields": []
    }
  ]